llama_index/readers/patentsview/__init__.py
llama_index/readers/patentsview/base.py
llama_index_readers_patentsview-1.0.0.dist-info/METADATA
llama_index_readers_patentsview-1.0.0.dist-info/WHEEL
llama_index_readers_patentsview-1.0.0.dist-info/licenses/LICENSE
llama_index_readers_patentsview-1.0.0.dist-info/RECORD
