Metadata-Version: 2.4
Name: llama-index-readers-patentsview
Version: 1.0.0
Summary: llama-index readers patentsview integration
Author-email: Your Name <you@example.com>
Maintainer: shao-shuai
License-Expression: MIT
License-File: LICENSE
Keywords: patent
Requires-Python: <4.0,>=3.9
Requires-Dist: llama-index-core<0.15,>=0.13.0
